telesign/__init__.py
telesign/messaging.py
telesign/phoneid.py
telesign/rest.py
telesign/score.py
telesign/util.py
telesign/voice.py
telesign-3.0.1.dist-info/LICENSE.txt
telesign-3.0.1.dist-info/METADATA
telesign-3.0.1.dist-info/WHEEL
telesign-3.0.1.dist-info/top_level.txt
telesign-3.0.1.dist-info/RECORD
